reyapi/__init__.py
reyapi/rall.py
reyapi/rbaidu/__init__.py
reyapi/rbaidu/rbaidu_base.py
reyapi/rbaidu/rbaidu_chat.py
reyapi/rbaidu/rbaidu_image.py
reyapi/rbaidu/rbaidu_voice.py
reyapi-0.41.dist-info/METADATA
reyapi-0.41.dist-info/WHEEL
reyapi-0.41.dist-info/top_level.txt
reyapi-0.41.dist-info/RECORD
