Metadata-Version: 2.4
Name: reyapi
Version: 0.41
Summary: Rey's API method set.
Home-page: https://github.com/reyxbo/reyapi/
Author: Rey
Author-email: reyxbo@163.com
Requires-Dist: reytool
Dynamic: author
Dynamic: author-email
Dynamic: home-page
Dynamic: requires-dist
Dynamic: summary
